pymidi_controller/__init__.py
pymidi_controller/cli.py
pymidi_controller/config.py
pymidi_controller/core.py
pymidi_controller/actions/__init__.py
pymidi_controller/actions/elgato.py
pymidi_controller/actions/elgato_discovery.py
pymidi_controller/actions/hue.py
pymidi_controller/actions/hue_discovery.py
pymidi_controller/data/default_config.yaml
pymidi_controller/data/systemd/pymidi-controller.service
pymidi_controller/utils/__init__.py
pymidi_controller/utils/color_cycle.py
pymidi_controller/utils/config_manager.py
pymidi_controller/utils/function_manager.py
pymidi_controller/utils/midi_utils.py
pymidi_controller/utils/service_manager.py
pymidi_controller/utils/state_manager.py
pymidi_controller-0.3.0.dist-info/licenses/LICENSE
pymidi_controller-0.3.0.dist-info/METADATA
pymidi_controller-0.3.0.dist-info/WHEEL
pymidi_controller-0.3.0.dist-info/entry_points.txt
pymidi_controller-0.3.0.dist-info/top_level.txt
pymidi_controller-0.3.0.dist-info/RECORD
