Metadata-Version: 2.4
Name: pymidi-controller
Version: 0.3.0
Summary: Daemon that maps MIDI events to system actions (Elgato, Hue, or custom functions).
Author-email: Alex Sandilands <sandilands.alex@gmail.com>
License-Expression: MIT
Project-URL: Homepage, https://github.com/AlexSandilands/pymidi-controller
Project-URL: Bug Tracker, https://github.com/AlexSandilands/pymidi-controller/issues
Classifier: Programming Language :: Python :: 3
Classifier: Operating System :: POSIX :: Linux
Classifier: Topic :: Multimedia :: Sound/Audio :: MIDI
Classifier: Topic :: Home Automation
Classifier: Topic :: System :: Hardware :: Hardware Drivers
Classifier: Topic :: Utilities
Requires-Python: >=3.7
License-File: LICENSE
Requires-Dist: mido>=1.2.10
Requires-Dist: python-rtmidi>=1.4.10
Requires-Dist: requests>=2.0
Requires-Dist: zeroconf>=0.40
Requires-Dist: PyYAML>=6.0
Dynamic: license-file
